release_tracker/TODO.md
release_tracker/__init__.py
release_tracker/admin.py
release_tracker/apps.py
release_tracker/github.py
release_tracker/heroku.py
release_tracker/management/__init__.py
release_tracker/management/commands/__init__.py
release_tracker/management/commands/fetch_heroku_releases.py
release_tracker/management/commands/stash_current_release.py
release_tracker/migrations/0001_initial.py
release_tracker/migrations/__init__.py
release_tracker/models.py
release_tracker/settings.py
release_tracker/templates/admin/release_tracker/herokurelease/change_form.html
release_tracker/urls.py
release_tracker/views.py
django_release_tracker-0.2.0.dist-info/LICENSE
django_release_tracker-0.2.0.dist-info/METADATA
django_release_tracker-0.2.0.dist-info/WHEEL
django_release_tracker-0.2.0.dist-info/RECORD
