Metadata-Version: 2.1
Name: django-release-tracker
Version: 0.2.0
Summary: Django app for syncing Heroku and Github releases.
Home-page: https://github.com/yunojuno/django-release-tracker
License: MIT
Author: YunoJuno
Author-email: code@yunojuno.com
Maintainer: YunoJuno
Maintainer-email: code@yunojuno.com
Requires-Python: >=3.10,<4.0
Classifier: Development Status :: 4 - Beta
Classifier: Environment :: Web Environment
Classifier: Framework :: Django
Classifier: Framework :: Django :: 3.2
Classifier: Framework :: Django :: 4.0
Classifier: Framework :: Django :: 4.1
Classifier: Framework :: Django :: 4.2
Classifier: Framework :: Django :: 5.0
Classifier: License :: OSI Approved :: MIT License
Classifier: Operating System :: OS Independent
Classifier: Programming Language :: Python :: 3
Classifier: Programming Language :: Python :: 3.10
Classifier: Programming Language :: Python :: 3.11
Classifier: Programming Language :: Python :: 3 :: Only
Classifier: Programming Language :: Python :: 3.12
Provides-Extra: heroku
Provides-Extra: local
Requires-Dist: dateparser
Requires-Dist: dj-database-url ; extra == "heroku"
Requires-Dist: django (>=3.2,<6.0)
Requires-Dist: gunicorn ; extra == "heroku"
Requires-Dist: psycopg2 ; extra == "heroku"
Requires-Dist: requests
Project-URL: Documentation, https://github.com/yunojuno/django-release-tracker
Project-URL: Repository, https://github.com/yunojuno/django-release-tracker
